screenshotbase/__init__.py
screenshotbase/client.py
screenshotbase-0.1.1.dist-info/METADATA
screenshotbase-0.1.1.dist-info/WHEEL
screenshotbase-0.1.1.dist-info/top_level.txt
screenshotbase-0.1.1.dist-info/RECORD
