Metadata-Version: 2.4
Name: screenshotbase
Version: 0.1.1
Summary: Python client for screenshotbase.com API
Home-page: https://screenshotbase.com/docs/
Author: ScreenshotBase
Author-email: support@screenshotbase.com
License: MIT
Project-URL: Documentation, https://screenshotbase.com/docs/
Classifier: Programming Language :: Python :: 3
Classifier: License :: OSI Approved :: MIT License
Classifier: Operating System :: OS Independent
Classifier: Programming Language :: Python :: 3 :: Only
Requires-Python: >=3.8
Requires-Dist: requests>=2.31.0
Dynamic: author
Dynamic: author-email
Dynamic: classifier
Dynamic: description
Dynamic: description-content-type
Dynamic: home-page
Dynamic: license
Dynamic: project-url
Dynamic: requires-dist
Dynamic: requires-python
Dynamic: summary
